caller/__main__.py
nakurite/__main__.py
nakuritycore/__init__.py
nakuritycore/core/__init__.py
nakuritycore/core/__main__.py
nakuritycore/core/devy.py
nakuritycore/core/nakuly.py
nakuritycore/core/nakurity.py
nakuritycore/core/pyguard.py
nakuritycore/core/requirement.py
nakuritycore/core/plugins/manager.py
nakuritycore/data/config/__init__.py
nakuritycore/data/config/loader.py
nakuritycore/data/config/logging.py
nakuritycore/data/config/tracer.py
nakuritycore/data/defaults/__init__.py
nakuritycore/data/defaults/configuration.py
nakuritycore/plugins/neurointegration/__init__.py
nakuritycore/plugins/neurointegration/abstract/__init__.py
nakuritycore/plugins/neurointegration/abstract/backend.py
nakuritycore/plugins/neurointegration/abstract/linker.py
nakuritycore/plugins/neurointegration/abstract/addons/vision.py
nakuritycore/plugins/neurointegration/implementation/__init__.py
nakuritycore/plugins/neurointegration/implementation/backend.py
nakuritycore/plugins/neurointegration/implementation/linker.py
nakuritycore/plugins/neurointegration/implementation/addons/vision.py
nakuritycore/utils/__init__.py
nakuritycore/utils/tracer.py
nakuritycore/utils/config/__init__.py
nakuritycore/utils/config/autodetect.py
nakuritycore/utils/config/simple.py
nakuritycore/utils/config/loader/__init__.py
nakuritycore/utils/config/loader/json.py
nakuritycore/utils/config/loader/toml.py
nakuritycore/utils/config/loader/yaml.py
nakuritycore/utils/logging/__init__.py
nakuritycore/utils/logging/logger.py
nakuritycore/utils/ws/__init__.py
nakuritycore/utils/ws/abstract/client.py
nakuritycore/utils/ws/abstract/server.py
nakuritycore-0.1.6.dist-info/METADATA
nakuritycore-0.1.6.dist-info/WHEEL
nakuritycore-0.1.6.dist-info/top_level.txt
nakuritycore-0.1.6.dist-info/RECORD
