Metadata-Version: 2.4
Name: nakuritycore
Version: 0.1.6
Summary: A core utility for all projects maintained by me! (Nakurity)
Author-email: Nakurity <nakurity@nakashireyumi.com>
License: MIT
Project-URL: Homepage, https://nakurity.com/nakuritycore
Project-URL: Repository, https://github.com/nakurity/nakuritycore
Project-URL: Issues, https://github.com/nakurity/nakuritycore/issues
Requires-Python: >=3.10
Requires-Dist: PyYAML>=6.0.3
Requires-Dist: websockets>=15.0.1
Requires-Dist: neuro_api>=2.2.1
Requires-Dist: pytesseract>=0.3.13
Requires-Dist: aiohttp>=3.13.1
Requires-Dist: pillow>=12.0.0
Requires-Dist: trio>=0.31.0
Provides-Extra: dev
Requires-Dist: pytest>=7.0; extra == "dev"
Requires-Dist: black>=24.0; extra == "dev"
Requires-Dist: mypy>=1.0; extra == "dev"
